qtarmsim/__init__.py
qtarmsim/_version.py
qtarmsim/mainwindow.py
qtarmsim/modulepath.py
qtarmsim/post_install.py
qtarmsim/qtarmsim.pro
qtarmsim/utils.py
qtarmsim/armsim/Firmware.o
qtarmsim/armsim/FirmwareAPI.txt
qtarmsim/armsim/GPL.txt
qtarmsim/armsim/LICENSE.txt
qtarmsim/armsim/coder.rb
qtarmsim/armsim/core.rb
qtarmsim/armsim/instruction.rb
qtarmsim/armsim/memory.rb
qtarmsim/armsim/memory_Defs.rb
qtarmsim/armsim/memory_block.rb
qtarmsim/armsim/read_ELF.rb
qtarmsim/armsim/server.rb
qtarmsim/armsim/thumbII_Defs.rb
qtarmsim/comm/__init__.py
qtarmsim/comm/armsimconnector.py
qtarmsim/comm/exceptions.py
qtarmsim/comm/mysocket.py
qtarmsim/comm/responses.py
qtarmsim/examples/01_Registers/01_add.s
qtarmsim/examples/02_Memory/01_add.s
qtarmsim/examples/02_Memory/02_stack.s
qtarmsim/examples/03_LCD/01_hello_world.s
qtarmsim/examples/03_LCD/02_ascii.s
qtarmsim/examples/03_LCD/03_printf.s
qtarmsim/examples/04_Floating_point/01_fmul.s
qtarmsim/examples/04_Floating_point/02_triangle.s
qtarmsim/gcc-arm/README.rst
qtarmsim/gcc-arm/download_and_prune.sh
qtarmsim/gcc-arm/linux32/README
qtarmsim/gcc-arm/linux32/arm-none-eabi/bin/as
qtarmsim/gcc-arm/linux32/bin/arm-none-eabi-gcc
qtarmsim/gcc-arm/linux32/lib/gcc/arm-none-eabi/4.4.1/__empty_dir__
qtarmsim/gcc-arm/linux32/libexec/gcc/arm-none-eabi/4.4.1/collect2
qtarmsim/gcc-arm/linux64/license.txt
qtarmsim/gcc-arm/linux64/arm-none-eabi/bin/as
qtarmsim/gcc-arm/linux64/bin/arm-none-eabi-gcc
qtarmsim/gcc-arm/linux64/lib/gcc/arm-none-eabi/13.2.1/__empty_dir__
qtarmsim/gcc-arm/linux64/libexec/gcc/arm-none-eabi/13.2.1/cc1
qtarmsim/gcc-arm/linux64/libexec/gcc/arm-none-eabi/13.2.1/collect2
qtarmsim/gcc-arm/linuxARM/arm-none-eabi/bin/as
qtarmsim/gcc-arm/linuxARM/bin/arm-none-eabi-gcc
qtarmsim/gcc-arm/linuxARM/lib/gcc/arm-none-eabi/13.2.1/__empty_dir__
qtarmsim/gcc-arm/linuxARM/libexec/gcc/arm-none-eabi/13.2.1/cc1
qtarmsim/gcc-arm/linuxARM/libexec/gcc/arm-none-eabi/13.2.1/collect2
qtarmsim/gcc-arm/macos/arm-none-eabi/bin/as
qtarmsim-1.0.5.dist-info/METADATA
qtarmsim-1.0.5.dist-info/WHEEL
qtarmsim-1.0.5.dist-info/entry_points.txt
qtarmsim-1.0.5.dist-info/RECORD
