Metadata-Version: 2.4
Name: qtarmsim
Version: 1.0.5
Summary: Easy to use graphical ARM simulator
Project-URL: Homepage, https://lorca.act.uji.es/project/qtarmsim/
Author-email: Sergio Barrachina Mir <barrachi@uji.es>
License: GPLV3+
Keywords: ARM,assembler,debugger,disassembler,simulator
Classifier: Development Status :: 5 - Production/Stable
Classifier: Intended Audience :: Education
Classifier: License :: OSI Approved :: GNU General Public License v2 (GPLv2)
Classifier: License :: OSI Approved :: GNU General Public License v3 or later (GPLv3+)
Classifier: Programming Language :: Python :: 3
Classifier: Programming Language :: Python :: 3.11
Classifier: Programming Language :: Python :: 3.12
Classifier: Programming Language :: Python :: 3.13
Classifier: Topic :: Software Development :: Assemblers
Classifier: Topic :: Software Development :: Debuggers
Classifier: Topic :: Software Development :: Disassemblers
Classifier: Topic :: System :: Emulators
Requires-Python: >=3.11
Requires-Dist: pyside6~=6.6.0
Requires-Dist: pywin32>=1.0; platform_system == 'Windows'
